setup.py
dbg_utils/__init__.py
dbg_utils/config.py
dbg_utils/env_trans.py
dbg_utils/idp_server.py
dbg_utils.egg-info/PKG-INFO
dbg_utils.egg-info/SOURCES.txt
dbg_utils.egg-info/dependency_links.txt
dbg_utils.egg-info/top_level.txt